<?xml version='1.0' encoding='UTF-8'?><magicdraw><activityparameternode id="0efb5095-f271-4fb0-9d0a-a5e98d573e66" refElementId="0efb5095-f271-4fb0-9d0a-a5e98d573e66" humanType="Activity Parameter Node" classType="ActivityParameterNode" requireSort="node" icon="index_files/icon_activityparameternode_948110109.jpg"><visibility humanName="Visibility">public</visibility><qualifiedName humanName="Qualified Name" mode="e">Process::Perform Cyber Resilience Requirements Methodology (CRRM)::Perform Cyber Resilience Requirements Methodology (CRRM)::Perform Verification &amp; Test Assessment::Requirments</qualifiedName><parameter refid="6c013df6-4112-4c37-90b5-04e2c4833827" refElementId="6c013df6-4112-4c37-90b5-04e2c4833827" humanType="Parameter" classType="Parameter" name="Requirments" icon="index_files/icon_parameter_1871846962.jpg" humanName="Parameter" mode="s,e"/><owner refid="18601d5c-011a-430b-b6aa-667ea5accb36" refElementId="18601d5c-011a-430b-b6aa-667ea5accb36" humanType="Activity" classType="Activity" name="Perform Verification &amp; Test Assessment" hasDiagram="true" icon="index_files/icon_activity_935955788.jpg" humanName="Owner" mode="s,e"/><outgoing humanName="Outgoing"><objectflow refid="d09406f0-21b1-42b1-b46a-5c70df7e73e3" refElementId="d09406f0-21b1-42b1-b46a-5c70df7e73e3" humanType="Object Flow" classType="ObjectFlow" name="Object Flow[Requirments -> input1]" isRelationship="true" icon="index_files/icon_objectflow_1864548849.jpg"/></outgoing><ordering humanName="Ordering" mode="e">FIFO</ordering><name humanName="Name" mode="s,e">Requirments</name><isLeaf humanName="Is Leaf">false</isLeaf><isControlType humanName="Is Control Type" mode="e">false</isControlType><documentation humanName="Documentation"></documentation><activity refid="18601d5c-011a-430b-b6aa-667ea5accb36" refElementId="18601d5c-011a-430b-b6aa-667ea5accb36" humanType="Activity" classType="Activity" name="Perform Verification &amp; Test Assessment" hasDiagram="true" icon="index_files/icon_activity_935955788.jpg" humanName="Activity"/><TYPE_MODIFIER humanName="Type Modifier"></TYPE_MODIFIER><TO_DO humanName="To Do" mode="s,e"></TO_DO><ActiveHyperlink humanName="Active Hyperlink"></ActiveHyperlink><report_appliedStereotype_tags humanName="Applied Stereotype" requireSort="element" mode="s,e"/></activityparameternode></magicdraw>