<?xml version='1.0' encoding='UTF-8'?><magicdraw><trigger id="36fcbfa5-21bc-4f79-b79d-c9cc15712133" refElementId="36fcbfa5-21bc-4f79-b79d-c9cc15712133" humanType="Trigger" classType="Trigger" requireSort="node" icon="index_files/icon_trigger_1006167107.jpg"><visibility humanName="Visibility">public</visibility><qualifiedName humanName="Qualified Name">Systems::A2::A2 Control Structure::A2::Obstacle::Seismic Sensor::Sesimic Sensor::::::::::</qualifiedName><owner refid="f861ab3e-98c8-4c3b-b49d-64a297a5c876" refElementId="f861ab3e-98c8-4c3b-b49d-64a297a5c876" humanType="Transition" classType="Transition" name="Transition:No Activity[SS: Vehicle Activity -> SS: No Activity]" isRelationship="true" icon="index_files/icon_transition_288756266.jpg" humanName="Owner" mode="s,e"/><name humanName="Name" mode="s,e"></name><event refid="b19753e7-1ff3-4c47-b369-c20672fa2119" refElementId="b19753e7-1ff3-4c47-b369-c20672fa2119" humanType="Signal Event" classType="SignalEvent" name="SignalEvent No Activity" icon="index_files/icon_signalevent_164417092.jpg" humanName="Event"/><documentation humanName="Documentation"></documentation><TO_DO humanName="To Do"></TO_DO><ActiveHyperlink humanName="Active Hyperlink"></ActiveHyperlink><eventType humanName="Event Type" mode="s,e">SignalEvent</eventType><report_appliedStereotype_tags humanName="Applied Stereotype" requireSort="element" mode="s,e"/></trigger></magicdraw>