<?xml version='1.0' encoding='UTF-8'?><magicdraw><extensionend id="6075e2a7-ef44-49e3-a733-2014e2699f9f" refElementId="6075e2a7-ef44-49e3-a733-2014e2699f9f" humanType="Extension End" classType="ExtensionEnd" requireSort="node" icon="index_files/icon_extensionend_1327170644.jpg"><visibility humanName="Visibility">private</visibility><upperValue refid="f8d0bdb9-0eaf-4fb8-8559-8019d0218528" refElementId="f8d0bdb9-0eaf-4fb8-8559-8019d0218528" humanType="Literal Unlimited Natural" classType="LiteralUnlimitedNatural" name="1" text="1" icon="index_files/icon_literalunlimitednatural_1543615404.jpg" humanName="Upper Value"/><upper humanName="Upper">1</upper><type refid="5048f71a-7d59-48c2-b89a-f69f363d7df9" refElementId="5048f71a-7d59-48c2-b89a-f69f363d7df9" humanType="Stereotype" classType="Stereotype" name="PathRedundancy" icon="index_files/icon_stereotype_850630993.jpg" humanName="Type"/><redefinitionContext humanName="Redefinition Context"><extension refid="e6437422-48d2-4910-a623-9d1c5d32f25e" refElementId="e6437422-48d2-4910-a623-9d1c5d32f25e" humanType="Extension" classType="Extension" name="Extension[extension_Path Redundancy:PathRedundancy - base_Connector:Connector]" isRelationship="true" icon="index_files/icon_extension_1763508892.jpg"/></redefinitionContext><qualifiedName humanName="Qualified Name">Resilience Profile::::extension_Path Redundancy</qualifiedName><owningAssociation refid="e6437422-48d2-4910-a623-9d1c5d32f25e" refElementId="e6437422-48d2-4910-a623-9d1c5d32f25e" humanType="Extension" classType="Extension" name="Extension[extension_Path Redundancy:PathRedundancy - base_Connector:Connector]" isRelationship="true" icon="index_files/icon_extension_1763508892.jpg" humanName="Owning Association"/><owner refid="e6437422-48d2-4910-a623-9d1c5d32f25e" refElementId="e6437422-48d2-4910-a623-9d1c5d32f25e" humanType="Extension" classType="Extension" name="Extension[extension_Path Redundancy:PathRedundancy - base_Connector:Connector]" isRelationship="true" icon="index_files/icon_extension_1763508892.jpg" humanName="Owner"/><ownedElement humanName="Owned Element"><literalinteger refid="ad9d4f4d-d9fc-4cf1-b7cd-d9dfb4ead073" refElementId="ad9d4f4d-d9fc-4cf1-b7cd-d9dfb4ead073" humanType="Literal Integer" classType="LiteralInteger" name="0" text="0" icon="index_files/icon_literalinteger_602632507.jpg"/><literalunlimitednatural refid="f8d0bdb9-0eaf-4fb8-8559-8019d0218528" refElementId="f8d0bdb9-0eaf-4fb8-8559-8019d0218528" humanType="Literal Unlimited Natural" classType="LiteralUnlimitedNatural" name="1" text="1" icon="index_files/icon_literalunlimitednatural_1543615404.jpg"/></ownedElement><opposite refid="0611e40f-91e7-4282-9d89-fb3d0909e05b" refElementId="0611e40f-91e7-4282-9d89-fb3d0909e05b" humanType="Property" classType="Property" name="base_Connector" icon="index_files/icon_property_1602862262.jpg" humanName="Opposite"/><namespace refid="e6437422-48d2-4910-a623-9d1c5d32f25e" refElementId="e6437422-48d2-4910-a623-9d1c5d32f25e" humanType="Extension" classType="Extension" name="Extension[extension_Path Redundancy:PathRedundancy - base_Connector:Connector]" isRelationship="true" icon="index_files/icon_extension_1763508892.jpg" humanName="Namespace"/><name humanName="Name">extension_Path Redundancy</name><multiplicity humanName="Multiplicity" mode="s,e">0..1</multiplicity><lowerValue refid="ad9d4f4d-d9fc-4cf1-b7cd-d9dfb4ead073" refElementId="ad9d4f4d-d9fc-4cf1-b7cd-d9dfb4ead073" humanType="Literal Integer" classType="LiteralInteger" name="0" text="0" icon="index_files/icon_literalinteger_602632507.jpg" humanName="Lower Value"/><lower humanName="Lower">0</lower><isUnique humanName="Is Unique">true</isUnique><isStatic humanName="Is Static">false</isStatic><isReadOnly humanName="Is Read Only">false</isReadOnly><isOrdered humanName="Is Ordered">false</isOrdered><isLeaf humanName="Is Leaf">false</isLeaf><isID humanName="Is ID" mode="s,e">false</isID><isDerivedUnion humanName="Is Derived Union">false</isDerivedUnion><isDerived humanName="Is Derived">false</isDerived><isComposite humanName="Is Composite">true</isComposite><featuringClassifier refid="e6437422-48d2-4910-a623-9d1c5d32f25e" refElementId="e6437422-48d2-4910-a623-9d1c5d32f25e" humanType="Extension" classType="Extension" name="Extension[extension_Path Redundancy:PathRedundancy - base_Connector:Connector]" isRelationship="true" icon="index_files/icon_extension_1763508892.jpg" humanName="Featuring Classifier"/><effectiveIRI humanName="Effective IRI"></effectiveIRI><documentation humanName="Documentation"></documentation><association refid="e6437422-48d2-4910-a623-9d1c5d32f25e" refElementId="e6437422-48d2-4910-a623-9d1c5d32f25e" humanType="Extension" classType="Extension" name="Extension[extension_Path Redundancy:PathRedundancy - base_Connector:Connector]" isRelationship="true" icon="index_files/icon_extension_1763508892.jpg" humanName="Association"/><aggregation humanName="Aggregation">composite</aggregation><TYPE_MODIFIER humanName="Type Modifier"></TYPE_MODIFIER><TO_DO humanName="To Do"></TO_DO><ActiveHyperlink humanName="Active Hyperlink"></ActiveHyperlink><ownedBy refid="e6437422-48d2-4910-a623-9d1c5d32f25e" refElementId="e6437422-48d2-4910-a623-9d1c5d32f25e" humanType="Extension" classType="Extension" name="Extension[extension_Path Redundancy:PathRedundancy - base_Connector:Connector]" isRelationship="true" icon="index_files/icon_extension_1763508892.jpg" humanName="Owned By" mode="s,e"/><navigable humanName="Navigable">true</navigable><report_appliedStereotype_tags humanName="Applied Stereotype" requireSort="element"/></extensionend></magicdraw>